jpeg_converter-1.0.1.dist-info/METADATA
jpeg_converter-1.0.1.dist-info/WHEEL
jpeg_converter-1.0.1.dist-info/license_files/LICENSE
jpeg_converter/__init__.py
jpeg_converter/jpeg_converter.cpython-310-x86_64-linux-gnu.so
jpeg_converter-1.0.1.dist-info/RECORD
