Metadata-Version: 2.1
Name: jpeg_converter
Version: 1.0.1
Classifier: Programming Language :: Rust
Classifier: Programming Language :: Python :: Implementation :: CPython
Classifier: Programming Language :: Python :: Implementation :: PyPy
Requires-Dist: numpy>=1.13.3
License-File: LICENSE
Requires-Python: >=3.8
